django_model_builder_service/__init__.py
django_model_builder_service/admin.py
django_model_builder_service/app_globals.py
django_model_builder_service/apps.py
django_model_builder_service/models.py
django_model_builder_service/startup.py
django_model_builder_service/tests.py
django_model_builder_service/urls.py
django_model_builder_service/views.py
django_model_builder_service/common/__init__.py
django_model_builder_service/common/logger.py
django_model_builder_service/config/__init__.py
django_model_builder_service/config/config_manager.py
django_model_builder_service/exceptions/ModelNotBuildError.py
django_model_builder_service/exceptions/__init__.py
django_model_builder_service/metrics/__init__.py
django_model_builder_service/metrics/metrics.py
django_model_builder_service/migrations/0001_initial.py
django_model_builder_service/migrations/__init__.py
django_model_builder_service/schedule_task/__init__.py
django_model_builder_service/schedule_task/schedule_task_manager.py
django_model_builder_service/services/__init__.py
django_model_builder_service/services/builder/__init__.py
django_model_builder_service/services/builder/builder.py
django_model_builder_service/services/monitoring/__init__.py
django_model_builder_service/services/monitoring/monitoring.py
django_model_builder_service/services/retention/__init__.py
django_model_builder_service/services/retention/retention.py
django_model_builder_service/templates/service/model.html
django_model_builder_service/templatetags/__init__.py
django_model_builder_service/templatetags/extras.py
tests/__init__.py
tests/dummy_objects.py
tests/test_api.py
tests/test_builder_service.py
tests/test_metrics_registrar.py
tests/test_schedule_task_manager.py
tests/test_utils.py
django_model_builder_service-1.0.57.0.dist-info/LICENSE
django_model_builder_service-1.0.57.0.dist-info/METADATA
django_model_builder_service-1.0.57.0.dist-info/WHEEL
django_model_builder_service-1.0.57.0.dist-info/top_level.txt
django_model_builder_service-1.0.57.0.dist-info/RECORD
